nn_visualizer/__init__.py
nn_visualizer/visualizer.py
unique_nn_visualizer-0.4.dist-info/METADATA
unique_nn_visualizer-0.4.dist-info/WHEEL
unique_nn_visualizer-0.4.dist-info/top_level.txt
unique_nn_visualizer-0.4.dist-info/RECORD
